jetforce_client.py
jetforce/__init__.py
jetforce/__main__.py
jetforce/__version__.py
jetforce/protocol.py
jetforce/py.typed
jetforce/server.py
jetforce/tls.py
jetforce/app/__init__.py
jetforce/app/base.py
jetforce/app/composite.py
jetforce/app/static.py
jetforce-1.0.0.dist-info/licenses/LICENSE
jetforce-1.0.0.dist-info/METADATA
jetforce-1.0.0.dist-info/WHEEL
jetforce-1.0.0.dist-info/entry_points.txt
jetforce-1.0.0.dist-info/top_level.txt
jetforce-1.0.0.dist-info/RECORD
