Metadata-Version: 2.4
Name: Jetforce
Version: 1.0.0
Summary: An Experimental Gemini Server
Author-email: Michael Lazar <lazar.michael22@gmail.com>
License: Other/Proprietary License
Project-URL: Homepage, https://github.com/michael-lazar/jetforce
Keywords: gemini,server,tcp,gopher,asyncio
Classifier: Environment :: Web Environment
Classifier: Intended Audience :: Developers
Classifier: Operating System :: OS Independent
Classifier: Programming Language :: Python
Classifier: Programming Language :: Python :: 3
Classifier: Topic :: Internet :: WWW/HTTP :: Dynamic Content
Classifier: Topic :: Software Development :: Libraries :: Python Modules
Requires-Python: >=3.9
License-File: LICENSE
Requires-Dist: twisted>=21.7.0
Requires-Dist: service_identity
Requires-Dist: idna
Requires-Dist: pyopenssl
Dynamic: license-file
